cowtif/__init__.py
cowtif-0.0.0.dist-info/LICENSE
cowtif-0.0.0.dist-info/METADATA
cowtif-0.0.0.dist-info/WHEEL
cowtif-0.0.0.dist-info/top_level.txt
cowtif-0.0.0.dist-info/RECORD
